rm_cmt_time/__init__.py
rm_cmt_time-0.1.0.dist-info/LICENSE
rm_cmt_time-0.1.0.dist-info/METADATA
rm_cmt_time-0.1.0.dist-info/WHEEL
rm_cmt_time-0.1.0.dist-info/top_level.txt
rm_cmt_time-0.1.0.dist-info/RECORD
